ispyb/__init__.py
ispyb/factory.py
ispyb/generators.py
ispyb/strictordereddict.py
ispyb/xmltools.py
ispyb/cli/__init__.py
ispyb/cli/job.py
ispyb/cli/last_data_collections_on.py
ispyb/connector/__init__.py
ispyb/connector/mysqlsp/__init__.py
ispyb/connector/mysqlsp/main.py
ispyb/connector/ws/__init__.py
ispyb/connector/ws/main.py
ispyb/interface/__init__.py
ispyb/interface/acquisition.py
ispyb/interface/connection.py
ispyb/interface/core.py
ispyb/interface/dataarea.py
ispyb/interface/factory.py
ispyb/interface/processing.py
ispyb/interface/screening.py
ispyb/interface/shipping.py
ispyb/sp/__init__.py
ispyb/sp/acquisition.py
ispyb/sp/core.py
ispyb/sp/emacquisition.py
ispyb/sp/mxacquisition.py
ispyb/sp/mxprocessing.py
ispyb/sp/mxscreening.py
ispyb/sp/shipping.py
ispyb/sp/xtalimaging.py
ispyb/sqlalchemy/__init__.py
ispyb/sqlalchemy/_auto_db_schema.py
ispyb/ws/__init__.py
ispyb-11.1.1.data/scripts/dimple2ispyb.py
ispyb-11.1.1.data/scripts/mxdatareduction2ispyb.py
ispyb-11.1.1.dist-info/licenses/LICENSE.md
ispyb-11.1.1.dist-info/METADATA
ispyb-11.1.1.dist-info/WHEEL
ispyb-11.1.1.dist-info/entry_points.txt
ispyb-11.1.1.dist-info/top_level.txt
ispyb-11.1.1.dist-info/RECORD
