Metadata-Version: 2.4
Name: ispyb
Version: 11.1.1
Summary: Python package to access ISPyB database
Author-email: Diamond Light Source <scientificsoftware@diamond.ac.uk>
License: Apache License 2.0
Project-URL: Documentation, https://ispyb.readthedocs.io
Project-URL: GitHub, https://github.com/DiamondLightSource/ispyb-api
Project-URL: Bug-Tracker, https://github.com/DiamondLightSource/ispyb-api/issues
Keywords: ISPyB,database
Classifier: Development Status :: 5 - Production/Stable
Classifier: License :: OSI Approved :: Apache Software License
Classifier: Programming Language :: Python :: 3
Classifier: Programming Language :: Python :: 3.7
Classifier: Programming Language :: Python :: 3.8
Classifier: Programming Language :: Python :: 3.9
Classifier: Programming Language :: Python :: 3.10
Classifier: Programming Language :: Python :: 3.11
Classifier: Operating System :: OS Independent
Classifier: Topic :: Software Development :: Libraries :: Python Modules
Requires-Python: >=3.10
License-File: LICENSE.md
Requires-Dist: mysql-connector-python>=8.0.32
Requires-Dist: sqlalchemy<3,>=2
Requires-Dist: tabulate
Dynamic: license-file
